django_encode-1.0.4.dist-info/DESCRIPTION.rst
django_encode-1.0.4.dist-info/METADATA
django_encode-1.0.4.dist-info/metadata.json
django_encode-1.0.4.dist-info/RECORD
django_encode-1.0.4.dist-info/top_level.txt
django_encode-1.0.4.dist-info/WHEEL
encode/__init__.py
encode/admin.py
encode/conf.py
encode/encoders.py
encode/forms.py
encode/models.py
encode/signals.py
encode/storage.py
encode/tasks.py
encode/util.py
encode/widgets.py
encode/locale/nl/LC_MESSAGES/django.mo
encode/locale/nl/LC_MESSAGES/django.po
encode/migrations/0001_initial.py
encode/migrations/0002_auto_20151125_1022.py
encode/migrations/__init__.py
encode/static/encode/js/media.js
encode/tests/__init__.py
encode/tests/celery.py
encode/tests/helpers.py
encode/tests/requirements.txt
encode/tests/runner.py
encode/tests/settings.py
encode/tests/test_admin.py
encode/tests/test_encoders.py
encode/tests/test_models.py
encode/tests/test_tasks.py
encode/tests/test_util.py
encode/tests/test_widgets.py
encode/tests/urls.py
