Metadata-Version: 2.0
Name: django-encode
Version: 1.0.4
Summary: Django media encoding.
Home-page: http://github.com/collab-project/django-encode
Author: Collab
Author-email: info@collab.nl
License: MIT
Platform: UNKNOWN
Classifier: Development Status :: 5 - Production/Stable
Classifier: Framework :: Django
Classifier: Intended Audience :: Developers
Classifier: License :: OSI Approved :: MIT License
Classifier: Operating System :: OS Independent
Classifier: Topic :: Software Development
Classifier: Programming Language :: Python :: 2
Classifier: Programming Language :: Python :: 2.7
Classifier: Programming Language :: Python :: 3
Classifier: Programming Language :: Python :: 3.3
Classifier: Programming Language :: Python :: 3.4
Requires-Dist: celery (>=3.1)
Requires-Dist: django-appconf (>=0.6)
Requires-Dist: django-queued-storage (>=0.8.0)
